<?xml version="1.0" encoding="UTF-8"?>
<osm version="0.6" generator="CGImap 0.8.3 (3702336 spike-07.openstreetmap.org)" copyright="OpenStreetMap and contributors" attribution="http://www.openstreetmap.org/copyright" license="http://opendatacommons.org/licenses/odbl/1-0/">
 <relation id="1114902" visible="true" version="49" changeset="79742116" timestamp="2020-01-18T21:29:34Z" user="Dinamik" uid="39040">
  <member type="way" ref="143832872" role="outer"/>
  <member type="way" ref="183080181" role="outer"/>
  <member type="way" ref="71338519" role="outer"/>
  <member type="way" ref="71338512" role="outer"/>
  <member type="way" ref="144799761" role="outer"/>
  <member type="way" ref="144799752" role="outer"/>
  <member type="way" ref="145739766" role="outer"/>
  <member type="way" ref="338078584" role="outer"/>
  <member type="way" ref="145012997" role="outer"/>
  <member type="way" ref="164553663" role="outer"/>
  <member type="way" ref="164553661" role="outer"/>
  <member type="way" ref="164553671" role="outer"/>
  <member type="way" ref="34348576" role="outer"/>
  <member type="way" ref="78518216" role="outer"/>
  <member type="way" ref="79570071" role="outer"/>
  <member type="way" ref="71360173" role="outer"/>
  <member type="way" ref="71360186" role="outer"/>
  <member type="way" ref="79570065" role="outer"/>
  <member type="way" ref="71376485" role="outer"/>
  <member type="way" ref="78334117" role="outer"/>
  <member type="way" ref="79570059" role="outer"/>
  <member type="way" ref="46835377" role="outer"/>
  <member type="way" ref="27755091" role="outer"/>
  <member type="way" ref="46835382" role="outer"/>
  <member type="way" ref="79570062" role="outer"/>
  <member type="way" ref="71338504" role="outer"/>
  <member type="way" ref="180061350" role="outer"/>
  <member type="way" ref="417334171" role="outer"/>
  <member type="way" ref="172289861" role="outer"/>
  <member type="way" ref="181364102" role="outer"/>
  <member type="way" ref="386927710" role="outer"/>
  <tag k="addr:country" v="RU"/>
  <tag k="addr:region" v="Санкт-Петербург"/>
  <tag k="admin_level" v="5"/>
  <tag k="boundary" v="administrative"/>
  <tag k="name" v="Центральный район"/>
  <tag k="name:pl" v="rejon centralny"/>
  <tag k="name:ru" v="Центральный район"/>
  <tag k="type" v="boundary"/>
  <tag k="url" v="http://www.gov.spb.ru/law?d&amp;nd=8414528&amp;nh=0&amp;header=010000004N01#I0"/>
  <tag k="wikidata" v="Q271014"/>
  <tag k="wikipedia" v="ru:Центральный район (Санкт-Петербург)"/>
 </relation>
</osm>